dapla_toolbelt_automation/__init__.py
dapla_toolbelt_automation/pubsub.py
dapla_toolbelt_automation/py.typed
dapla_toolbelt_automation-1.1.1.dist-info/WHEEL
dapla_toolbelt_automation-1.1.1.dist-info/entry_points.txt
dapla_toolbelt_automation-1.1.1.dist-info/METADATA
dapla_toolbelt_automation-1.1.1.dist-info/RECORD
