Metadata-Version: 2.4
Name: dapla-toolbelt-automation
Version: 1.1.1
Summary: Dapla Toolbelt Automation
Author: Dapla Developers
Author-email: Dapla Developers <dapla-platform-developers@ssb.no>
License-Expression: MIT
Classifier: Programming Language :: Python :: 3
Classifier: Programming Language :: Python :: 3.10
Classifier: Programming Language :: Python :: 3.11
Classifier: Programming Language :: Python :: 3.12
Classifier: Programming Language :: Python :: 3.13
Classifier: License :: OSI Approved :: MIT License
Classifier: Development Status :: 4 - Beta
Classifier: Typing :: Typed
Requires-Dist: click>=8.0.1
Requires-Dist: google-cloud-pubsub>=2.14.1
Requires-Dist: google-cloud-storage>=2.7.0
Requires-Dist: pytest>=8.4.2
Maintainer: Statistics Norway, Data enablement Department (724)
Requires-Python: >=3.10, <4.0
Project-URL: Changelog, https://github.com/statisticsnorway/dapla-toolbelt-automation/releases
Project-URL: documentation, https://statisticsnorway.github.io/dapla-toolbelt-automation
Project-URL: homepage, https://github.com/statisticsnorway/dapla-toolbelt-automation
Project-URL: repository, https://github.com/statisticsnorway/dapla-toolbelt-automation
